loadfig-0.1.0.dist-info/METADATA
loadfig-0.1.0.dist-info/WHEEL
loadfig-0.1.0.dist-info/entry_points.txt
loadfig/__init__.py
loadfig/_config.py
loadfig/_load.py
loadfig/error.py
loadfig/py.typed
loadfig/py.typed.license
loadfig-0.1.0.dist-info/RECORD
