Metadata-Version: 2.4
Name: loadfig
Version: 0.1.0
Summary: One-liner Python pyproject config loader. Lightweight, simple, and VCS-aware with root auto-discovery.
Author: open-nudge
Maintainer: open-nudge
License-Expression: Apache-2.0
Classifier: Development Status :: 2 - Pre-Alpha
Classifier: Intended Audience :: Developers
Classifier: Programming Language :: Python
Classifier: Programming Language :: Python :: 3 :: Only
Classifier: Programming Language :: Python :: 3.11
Classifier: Programming Language :: Python :: 3.12
Classifier: Programming Language :: Python :: 3.13
Classifier: Topic :: Software Development :: Libraries
Classifier: Topic :: Software Development :: Libraries :: Python Modules
Classifier: Typing :: Typed
Project-URL: Changelog, https://github.com/open-nudge/loadfig/blob/master/CHANGELOG.md
Project-URL: Documentation, https://open-nudge.github.io/loadfig
Project-URL: Homepage, https://open-nudge.github.io/loadfig
Project-URL: Issues, https://github.com/open-nudge/loadfig/issues
Project-URL: Repository, https://github.com/open-nudge/loadfig
Requires-Python: >=3.11
